py_xh_custapp_xethhung12/__init__.py
py_xh_custapp_xethhung12/__main__.py
py_xh_custapp_xethhung12/_pyXhCustApp.py
py_xh_custapp_xethhung12/_cmd/run.py
py_xh_custapp_xethhung12-1.4.8.dist-info/METADATA
py_xh_custapp_xethhung12-1.4.8.dist-info/WHEEL
py_xh_custapp_xethhung12-1.4.8.dist-info/entry_points.txt
py_xh_custapp_xethhung12-1.4.8.dist-info/licenses/LICENSE.txt
py_xh_custapp_xethhung12-1.4.8.dist-info/RECORD
