Metadata-Version: 2.4
Name: py-xh-custapp-xethhung12
Version: 1.4.8
Summary: Custom App Environment
Project-URL: Homepage, https://github.com/xh-dev-py/pyXhCustApp
Project-URL: Issues, https://github.com/xh-dev-py/pyXhCustApp/issues
Author-email: Xeth Hung <admin@xethh.me>
License-Expression: GPL-3.0-only
License-File: LICENSE.txt
Classifier: Operating System :: OS Independent
Classifier: Programming Language :: Python :: 3
Requires-Python: >=3.11
Requires-Dist: j-vault-http-client-xethhung12>=0.1.1
Requires-Dist: pycryptodome
